{
    "logaritmo": [
        {
            "taxaMes": 73,
            "valMultiplicadorMonteInicial": 889,
            "logTaxaMes": 0.24,
            "logValMultiplicadorMonteInicial": 2.95,
            "resposta": 12
        }
    ],
    "respostas": [
        {
            "letra": "a)",
            "resposta": -25,
            "correta": "Nao",
            "tipoerro": "gerada aleatoriamente e negativa"
        },
        {
            "letra": "b)",
            "resposta": -23,
            "correta": "Nao",
            "tipoerro": "gerada aleatoriamente e negativa"
        },
        {
            "letra": "c)",
            "resposta": 12,
            "correta": "Sim",
            "tipoerro": "nenhum"
        },
        {
            "letra": "d)",
            "resposta": 14,
            "correta": "Nao",
            "tipoerro": "gerada aleatoriamente e positiva"
        },
        {
            "letra": "e)",
            "resposta": 81,
            "correta": "Nao",
            "tipoerro": "invertida e positiva"
        }
    ],
    "atributosquestao": [
        {
            "enunciado": "O valor C de um capital (empregado a uma taxa i de juros capitalizados periodicamente ao fim do per\u00edodo), ap\u00f3s t per\u00edodos, \u00e9 dado por C = C<sub>0</sub> \u00d7 (1 + i)<sup>t</sup>, em que C<sub>0</sub> \u00e9 o valor inicial.\nQual \u00e9 o tempo necess\u00e1rio para que um capital empregado \u00e0 taxa de 73% ao m\u00eas, com juros capitalizados mensalmente, seja multiplicado por 889?\nAdmita que log(1.73) = 0.24 e log(889) = 2.95",
            "corretaspossiveis": 12,
            "corretas": 1,
            "aleatoriapositiva": 1,
            "aleatorianegativa": 2,
            "invertidapositiva": 1,
            "invertidanegativa": 0,
            "respostascorretas": "C"
        }
    ]
}