{
    "equacaoExponencial": [
        {
            "numBase": 4,
            "numMultiplicadorLogaritmando": 8,
            "numMultiplicadorBase": 7,
            "resposta": "2\u22c5\u221a14"
        }
    ],
    "respostas": [
        {
            "letra": "a)",
            "resposta": "-2\u22c5\u221a3",
            "correta": "Nao",
            "tipoerro": "gerada aleatoriamente e negativa"
        },
        {
            "letra": "b)",
            "resposta": "2\u22c5\u221a14",
            "correta": "Sim",
            "tipoerro": "nenhum"
        },
        {
            "letra": "c)",
            "resposta": "\u221a10",
            "correta": "Nao",
            "tipoerro": "gerada aleatoriamente e positiva"
        },
        {
            "letra": "d)",
            "resposta": "-9",
            "correta": "Nao",
            "tipoerro": "gerada aleatoriamente e negativa"
        },
        {
            "letra": "e)",
            "resposta": "2\u22c5\u221a7",
            "correta": "Nao",
            "tipoerro": "gerada aleatoriamente e positiva"
        }
    ],
    "atributosquestao": [
        {
            "enunciado": "(Fuvest-modificada) Temos que x > 1 tal que log<sub>x</sub>(65536) = log<sub>16384</sub>(x). Assim sendo, o logar\u00edtmo de x na base 10 \u00e9:",
            "corretaspossiveis": "2\u22c5\u221a14",
            "corretas": 1,
            "aleatoriapositiva": 2,
            "aleatorianegativa": 2,
            "invertidapositiva": 0,
            "invertidanegativa": 0,
            "respostascorretas": "B"
        }
    ]
}