{
    "equacaoExponencial": [
        {
            "numBase": 9,
            "numMultiplicadorLogaritmando": 6,
            "numMultiplicadorBase": 7,
            "resposta": "\u221a42"
        }
    ],
    "respostas": [
        {
            "letra": "a)",
            "resposta": "3\u22c5\u221a10",
            "correta": "Nao",
            "tipoerro": "gerada aleatoriamente e positiva"
        },
        {
            "letra": "b)",
            "resposta": "\u221a42",
            "correta": "Sim",
            "tipoerro": "nenhum"
        },
        {
            "letra": "c)",
            "resposta": "\u221a2",
            "correta": "Nao",
            "tipoerro": "invertida e positiva"
        },
        {
            "letra": "d)",
            "resposta": "\u221a30",
            "correta": "Nao",
            "tipoerro": "gerada aleatoriamente e positiva"
        },
        {
            "letra": "e)",
            "resposta": "2\u22c5\u221a10",
            "correta": "Nao",
            "tipoerro": "gerada aleatoriamente e positiva"
        }
    ],
    "atributosquestao": [
        {
            "enunciado": "(Fuvest-modificada) Temos que x > 1 tal que logx(531441) = log4782969(x). Assim sendo, o logar\u00edtmo de x em uma base qualquer \u00e9:",
            "corretaspossiveis": "\u221a42",
            "corretas": 1,
            "aleatoriapositiva": 3,
            "aleatorianegativa": 0,
            "invertidapositiva": 1,
            "invertidanegativa": 0,
            "respostascorretas": "B"
        }
    ]
}