{
    "logaritmo": [
        {
            "numBase": 206,
            "tipoDenominadorFracao": 2,
            "resposta": "\u221a206"
        }
    ],
    "respostas": [
        {
            "letra": "a)",
            "resposta": "\u221a30",
            "correta": "Nao",
            "tipoerro": "gerada aleatoriamente e positiva"
        },
        {
            "letra": "b)",
            "resposta": " 3 _____\n-\u2572\u2571 206 ",
            "correta": "Nao",
            "tipoerro": "invertida e negativa"
        },
        {
            "letra": "c)",
            "resposta": "-\u221a174",
            "correta": "Nao",
            "tipoerro": "gerada aleatoriamente e negativa"
        },
        {
            "letra": "d)",
            "resposta": "-4\u22c5\u221a5",
            "correta": "Nao",
            "tipoerro": "gerada aleatoriamente e negativa"
        },
        {
            "letra": "e)",
            "resposta": "\u221a206",
            "correta": "Sim",
            "tipoerro": "nenhum"
        }
    ],
    "atributosquestao": [
        {
            "enunciado": "A soma dos logaritmos de dois n\u00fameros na base 206 \u00e9 1/2. Determine o produto desses n\u00fameros.",
            "corretaspossiveis": "\u221a206",
            "corretas": 1,
            "aleatoriapositiva": 1,
            "aleatorianegativa": 2,
            "invertidapositiva": 0,
            "invertidanegativa": 1,
            "respostascorretas": "E"
        }
    ]
}