{
    "logaritmo": [
        {
            "numBase": 226,
            "tipoDenominadorFracao": 2,
            "resposta": "1.18"
        }
    ],
    "respostas": [
        {
            "letra": "a)",
            "resposta": "1.18",
            "correta": "Sim",
            "tipoerro": "nenhum"
        },
        {
            "letra": "b)",
            "resposta": "-4.71",
            "correta": "Nao",
            "tipoerro": "invertida e negativa"
        },
        {
            "letra": "c)",
            "resposta": "-1.05",
            "correta": "Nao",
            "tipoerro": "gerada aleatoriamente e negativa"
        },
        {
            "letra": "d)",
            "resposta": "-1.16",
            "correta": "Nao",
            "tipoerro": "gerada aleatoriamente e negativa"
        },
        {
            "letra": "e)",
            "resposta": "0.85",
            "correta": "Nao",
            "tipoerro": "gerada aleatoriamente e positiva"
        }
    ],
    "atributosquestao": [
        {
            "enunciado": "A soma dos logaritmos de dois n\u00fameros na base 226 \u00e9 1&frasl;<sub>2</sub>. Determine o logaritmo na base 10 do produto destes n\u00fameros.",
            "corretaspossiveis": "1.18",
            "corretas": 1,
            "aleatoriapositiva": 1,
            "aleatorianegativa": 2,
            "invertidapositiva": 0,
            "invertidanegativa": 1,
            "respostascorretas": "A"
        }
    ]
}