{
    "logaritmo": [
        {
            "numBase": 862,
            "tipoDenominadorFracao": 2,
            "resposta": "\u221a862"
        }
    ],
    "respostas": [
        {
            "letra": "a)",
            "resposta": "\u221a246",
            "correta": "Nao",
            "tipoerro": "gerada aleatoriamente e positiva"
        },
        {
            "letra": "b)",
            "resposta": "3 _____\n\u2572\u2571 735 ",
            "correta": "Nao",
            "tipoerro": "gerada aleatoriamente e positiva"
        },
        {
            "letra": "c)",
            "resposta": "5\u22c5\u221a3",
            "correta": "Nao",
            "tipoerro": "gerada aleatoriamente e positiva"
        },
        {
            "letra": "d)",
            "resposta": "2\u22c5\u221a177",
            "correta": "Nao",
            "tipoerro": "gerada aleatoriamente e positiva"
        },
        {
            "letra": "e)",
            "resposta": "\u221a862",
            "correta": "Sim",
            "tipoerro": "nenhum"
        }
    ],
    "atributosquestao": [
        {
            "enunciado": "A soma dos logaritmos de dois n\u00fameros na base 862 \u00e9 1/2. Determine o produto desses n\u00fameros.",
            "corretaspossiveis": "\u221a862",
            "corretas": 1,
            "aleatoriapositiva": 4,
            "aleatorianegativa": 0,
            "invertidapositiva": 0,
            "invertidanegativa": 0,
            "respostascorretas": "E"
        }
    ]
}