{
    "logaritmo": [
        {
            "numBase": 237,
            "tipoDenominadorFracao": 2,
            "resposta": "\u221a237"
        }
    ],
    "respostas": [
        {
            "letra": "a)",
            "resposta": "-\u221a78",
            "correta": "Nao",
            "tipoerro": "gerada aleatoriamente e negativa"
        },
        {
            "letra": "b)",
            "resposta": "3\u22c5\u221a15",
            "correta": "Nao",
            "tipoerro": "gerada aleatoriamente e positiva"
        },
        {
            "letra": "c)",
            "resposta": "-3\u22c5\u221a5",
            "correta": "Nao",
            "tipoerro": "gerada aleatoriamente e negativa"
        },
        {
            "letra": "d)",
            "resposta": "-5\u22c5\u221a3",
            "correta": "Nao",
            "tipoerro": "gerada aleatoriamente e negativa"
        },
        {
            "letra": "e)",
            "resposta": "\u221a237",
            "correta": "Sim",
            "tipoerro": "nenhum"
        }
    ],
    "atributosquestao": [
        {
            "enunciado": "A soma dos logaritmos de dois n\u00fameros na base 237 \u00e9 1&frasl;<sub>2</sub>. Determine o produto desses n\u00fameros.",
            "corretaspossiveis": "\u221a237",
            "corretas": 1,
            "aleatoriapositiva": 1,
            "aleatorianegativa": 3,
            "invertidapositiva": 0,
            "invertidanegativa": 0,
            "respostascorretas": "E"
        }
    ]
}