{
    "logaritmo": [
        {
            "numBase": 414,
            "tipoDenominadorFracao": 2,
            "resposta": "3\u22c5\u221a46"
        }
    ],
    "respostas": [
        {
            "letra": "a)",
            "resposta": "-3\u22c5\u221a46",
            "correta": "Nao",
            "tipoerro": "invertida e negativa"
        },
        {
            "letra": "b)",
            "resposta": "-2\u22c5\u221a53",
            "correta": "Nao",
            "tipoerro": "gerada aleatoriamente e negativa"
        },
        {
            "letra": "c)",
            "resposta": "\u221a402",
            "correta": "Nao",
            "tipoerro": "gerada aleatoriamente e positiva"
        },
        {
            "letra": "d)",
            "resposta": "-2\u22c5\u221a6",
            "correta": "Nao",
            "tipoerro": "gerada aleatoriamente e negativa"
        },
        {
            "letra": "e)",
            "resposta": "3\u22c5\u221a46",
            "correta": "Sim",
            "tipoerro": "nenhum"
        }
    ],
    "atributosquestao": [
        {
            "enunciado": "A soma dos logaritmos de dois n\u00fameros na base 414 \u00e9 1/2. Determine o produto desses n\u00fameros.",
            "corretaspossiveis": "3\u22c5\u221a46",
            "corretas": 1,
            "aleatoriapositiva": 1,
            "aleatorianegativa": 2,
            "invertidapositiva": 0,
            "invertidanegativa": 1,
            "respostascorretas": "E"
        }
    ]
}