{
    "logaritmo": [
        {
            "numBase": 78,
            "tipoDenominadorFracao": 2,
            "resposta": "\u221a78"
        }
    ],
    "respostas": [
        {
            "letra": "a)",
            "resposta": "\u221a33",
            "correta": "Nao",
            "tipoerro": "gerada aleatoriamente e positiva"
        },
        {
            "letra": "b)",
            "resposta": "-2\u22c5\u221a3",
            "correta": "Nao",
            "tipoerro": "gerada aleatoriamente e negativa"
        },
        {
            "letra": "c)",
            "resposta": "-\u221a51",
            "correta": "Nao",
            "tipoerro": "gerada aleatoriamente e negativa"
        },
        {
            "letra": "d)",
            "resposta": "-\u221a78",
            "correta": "Nao",
            "tipoerro": "invertida e negativa"
        },
        {
            "letra": "e)",
            "resposta": "\u221a78",
            "correta": "Sim",
            "tipoerro": "nenhum"
        }
    ],
    "atributosquestao": [
        {
            "enunciado": "A soma dos logaritmos de dois n\u00fameros na base 78 \u00e9 1/2. Determine o produto desses n\u00fameros.",
            "corretaspossiveis": "\u221a78",
            "corretas": 1,
            "aleatoriapositiva": 1,
            "aleatorianegativa": 2,
            "invertidapositiva": 0,
            "invertidanegativa": 1,
            "respostascorretas": "E"
        }
    ]
}