{
    "logaritmo": [
        {
            "numBase": 736,
            "tipoDenominadorFracao": 2,
            "resposta": "4\u22c5\u221a46"
        }
    ],
    "respostas": [
        {
            "letra": "a)",
            "resposta": "4\u22c5\u221a46",
            "correta": "Sim",
            "tipoerro": "nenhum"
        },
        {
            "letra": "b)",
            "resposta": " 3 _____\n-\u2572\u2571 406 ",
            "correta": "Nao",
            "tipoerro": "gerada aleatoriamente e negativa"
        },
        {
            "letra": "c)",
            "resposta": "\u221a138",
            "correta": "Nao",
            "tipoerro": "gerada aleatoriamente e positiva"
        },
        {
            "letra": "d)",
            "resposta": " 3 _____\n-\u2572\u2571 639 ",
            "correta": "Nao",
            "tipoerro": "gerada aleatoriamente e negativa"
        },
        {
            "letra": "e)",
            "resposta": "  3 ____\n2\u22c5\u2572\u2571 92 ",
            "correta": "Nao",
            "tipoerro": "invertida e positiva"
        }
    ],
    "atributosquestao": [
        {
            "enunciado": "A soma dos logaritmos de dois n\u00fameros na base 736 \u00e9 1/2. Determine o produto desses n\u00fameros.",
            "corretaspossiveis": "4\u22c5\u221a46",
            "corretas": 1,
            "aleatoriapositiva": 1,
            "aleatorianegativa": 2,
            "invertidapositiva": 1,
            "invertidanegativa": 0,
            "respostascorretas": "A"
        }
    ]
}