{
    "logaritmo": [
        {
            "numBase": 437,
            "tipoDenominadorFracao": 2,
            "resposta": "1.32"
        }
    ],
    "respostas": [
        {
            "letra": "a)",
            "resposta": "-1.02",
            "correta": "Nao",
            "tipoerro": "gerada aleatoriamente e negativa"
        },
        {
            "letra": "b)",
            "resposta": "-1.14",
            "correta": "Nao",
            "tipoerro": "gerada aleatoriamente e negativa"
        },
        {
            "letra": "c)",
            "resposta": "1.32",
            "correta": "Sim",
            "tipoerro": "nenhum"
        },
        {
            "letra": "d)",
            "resposta": "-0.45",
            "correta": "Nao",
            "tipoerro": "gerada aleatoriamente e negativa"
        },
        {
            "letra": "e)",
            "resposta": "1.28",
            "correta": "Nao",
            "tipoerro": "gerada aleatoriamente e positiva"
        }
    ],
    "atributosquestao": [
        {
            "enunciado": "A soma dos logaritmos de dois n\u00fameros na base 437 \u00e9 1&frasl;<sub>2</sub>. Determine o logaritmo na base 10 do produto destes n\u00fameros.",
            "corretaspossiveis": "1.32",
            "corretas": 1,
            "aleatoriapositiva": 1,
            "aleatorianegativa": 3,
            "invertidapositiva": 0,
            "invertidanegativa": 0,
            "respostascorretas": "C"
        }
    ]
}