{
    "equacaoExponencial": [
        {
            "radicando": 9034,
            "indice": 3,
            "expoente": 5,
            "resultado": "             2/3\n1 - 9034\u22c59034   "
        }
    ],
    "respostas": [
        {
            "letra": "a)",
            "resposta": "          3 _________\n1 - 17368\u22c5\u2572\u2571 9426482 ",
            "correta": "Nao",
            "tipoerro": "gerada aleatoriamente e positiva"
        },
        {
            "letra": "b)",
            "resposta": "             2/3\n1 - 9034\u22c59034   ",
            "correta": "Sim",
            "tipoerro": "nenhum"
        },
        {
            "letra": "c)",
            "resposta": "1 + 135663392\u22c5\u221a2059",
            "correta": "Nao",
            "tipoerro": "gerada aleatoriamente e negativa"
        },
        {
            "letra": "d)",
            "resposta": "             2/3\n1 - 4893\u22c54893   ",
            "correta": "Nao",
            "tipoerro": "gerada aleatoriamente e positiva"
        },
        {
            "letra": "e)",
            "resposta": "             2/3\n1 - 11168\u22c5349   ",
            "correta": "Nao",
            "tipoerro": "gerada aleatoriamente e positiva"
        }
    ],
    "atributosquestao": [
        {
            "enunciado": "A lei de decomposi\u00e7\u00e3o de um elemento X no tempo t \u2265 0 \u00e9 dada por M(t) = C.9034^(p.t), em que M(t) \u00e9 quantidade de X no tempo t; C, p s\u00e3o constantes positivas. Se a quantidade primitiva M(0), quando dividida por 9034, desaparece em 3 anos, qual a quantidade perdida em 5 anos?",
            "corretaspossiveis": "             2/3\n1 - 9034\u22c59034   ",
            "corretas": 1,
            "aleatoriapositiva": 3,
            "aleatorianegativa": 1,
            "invertidapositiva": 0,
            "invertidanegativa": 0,
            "respostascorretas": "B"
        }
    ]
}