{
    "equacaoExponencial": [
        {
            "radicando": 1835,
            "indice": 2,
            "expoente": 5,
            "resultado": "1 - 3367225\u22c5\u221a1835"
        }
    ],
    "respostas": [
        {
            "letra": "a)",
            "resposta": "1 + 555025\u22c5\u221a745",
            "correta": "Nao",
            "tipoerro": "gerada aleatoriamente e positiva"
        },
        {
            "letra": "b)",
            "resposta": "1 - 231361\u22c5\u221a481",
            "correta": "Nao",
            "tipoerro": "gerada aleatoriamente e negativa"
        },
        {
            "letra": "c)",
            "resposta": "1 - 3367225\u22c5\u221a1835",
            "correta": "Sim",
            "tipoerro": "nenhum"
        },
        {
            "letra": "d)",
            "resposta": "1 + 25600\u22c5\u221a5",
            "correta": "Nao",
            "tipoerro": "gerada aleatoriamente e positiva"
        },
        {
            "letra": "e)",
            "resposta": "1 - 828100\u22c5\u221a910",
            "correta": "Nao",
            "tipoerro": "gerada aleatoriamente e negativa"
        }
    ],
    "atributosquestao": [
        {
            "enunciado": "A lei de decomposi\u00e7\u00e3o de um elemento X no tempo t \u2265 0 \u00e9 dada por M(t) = C \u00d7 1835<sup>(p.t)</sup>, em que M(t) \u00e9 quantidade de X no tempo t; C, p s\u00e3o constantes positivas. Se a quantidade primitiva M(0), quando dividida por 1835, desaparece em 2 anos, qual a quantidade perdida em 5 anos?",
            "corretaspossiveis": "1 - 3367225\u22c5\u221a1835",
            "corretas": 1,
            "aleatoriapositiva": 2,
            "aleatorianegativa": 2,
            "invertidapositiva": 0,
            "invertidanegativa": 0,
            "respostascorretas": "C"
        }
    ]
}