{
    "equacaoExponencial": [
        {
            "radicando": 5754,
            "indice": 3,
            "expoente": 2,
            "resultado": "        2/3\n1 - 5754   "
        }
    ],
    "respostas": [
        {
            "letra": "a)",
            "resposta": "         2/3\n1 - 16\u22c539   ",
            "correta": "Nao",
            "tipoerro": "gerada aleatoriamente e positiva"
        },
        {
            "letra": "b)",
            "resposta": "        2/3\n1 - 5754   ",
            "correta": "Sim",
            "tipoerro": "nenhum"
        },
        {
            "letra": "c)",
            "resposta": "5755",
            "correta": "Nao",
            "tipoerro": "invertida e negativa"
        },
        {
            "letra": "d)",
            "resposta": "-5543",
            "correta": "Nao",
            "tipoerro": "gerada aleatoriamente e positiva"
        },
        {
            "letra": "e)",
            "resposta": "        2/3\n1 - 3791   ",
            "correta": "Nao",
            "tipoerro": "gerada aleatoriamente e positiva"
        }
    ],
    "atributosquestao": [
        {
            "enunciado": "A lei de decomposi\u00e7\u00e3o de um elemento X no tempo t \u2265 0 \u00e9 dada por M(t) = C.    p\u22c5t\n5754   , em que M(t) \u00e9 quantidade de X no tempo t; C, p s\u00e3o constantes positivas. Se a quantidade primitiva M(0), quando dividida por 5754, desaparece em 3 anos, qual a quantidade perdida em 2 anos?",
            "corretaspossiveis": "        2/3\n1 - 5754   ",
            "corretas": 1,
            "aleatoriapositiva": 3,
            "aleatorianegativa": 0,
            "invertidapositiva": 0,
            "invertidanegativa": 1,
            "respostascorretas": "B"
        }
    ]
}