{
    "equacaoExponencial": [
        {
            "radicando": 34,
            "indice": 3,
            "expoente": 5,
            "resultado": "         2/3\n1 - 34\u22c534   "
        }
    ],
    "respostas": [
        {
            "letra": "a)",
            "resposta": "        3 ___\n1 + 256\u22c5\u2572\u2571 2 ",
            "correta": "Nao",
            "tipoerro": "gerada aleatoriamente e negativa"
        },
        {
            "letra": "b)",
            "resposta": "1 - 196\u22c5\u221a14",
            "correta": "Nao",
            "tipoerro": "gerada aleatoriamente e positiva"
        },
        {
            "letra": "c)",
            "resposta": "         2/3\n1 - 14\u22c514   ",
            "correta": "Nao",
            "tipoerro": "gerada aleatoriamente e positiva"
        },
        {
            "letra": "d)",
            "resposta": "         2/3\n1 - 34\u22c534   ",
            "correta": "Sim",
            "tipoerro": "nenhum"
        },
        {
            "letra": "e)",
            "resposta": "1 + 25\u22c5\u221a5",
            "correta": "Nao",
            "tipoerro": "gerada aleatoriamente e negativa"
        }
    ],
    "atributosquestao": [
        {
            "enunciado": "A lei de decomposi\u00e7\u00e3o de um elemento X no tempo t \u2265 0 \u00e9 dada por M(t) = C.  p\u22c5t\n34   , em que M(t) \u00e9 quantidade de X no tempo t; C, p s\u00e3o constantes positivas. Se a quantidade primitiva M(0), quando dividida por 34, desaparece em 3 anos, qual a quantidade perdida em 5 anos?",
            "corretaspossiveis": "         2/3\n1 - 34\u22c534   ",
            "corretas": 1,
            "aleatoriapositiva": 2,
            "aleatorianegativa": 2,
            "invertidapositiva": 0,
            "invertidanegativa": 0,
            "respostascorretas": "D"
        }
    ]
}