{
    "logaritmo": [
        {
            "a": 84,
            "b": -7644,
            "c": 173376,
            "x1": 48,
            "x2": 43,
            "resposta": "S = [x \u2208 IR/ x = 48 ou x = 43]"
        }
    ],
    "respostas": [
        {
            "letra": "a)",
            "resposta": "S = [x \u2208 IR/ x = 34 ou x = -40]",
            "correta": "Nao",
            "tipoerro": "gerada aleatoriamente e negativa"
        },
        {
            "letra": "b)",
            "resposta": "S = [x \u2208 IR/ x = 48 ou x = 43]",
            "correta": "Sim",
            "tipoerro": "nenhum"
        },
        {
            "letra": "c)",
            "resposta": "S = [x \u2208 IR/ x = 78 ou x = -82]",
            "correta": "Nao",
            "tipoerro": "gerada aleatoriamente e negativa"
        },
        {
            "letra": "d)",
            "resposta": "S = [x \u2208 IR/ x = -30 ou x = -41]",
            "correta": "Nao",
            "tipoerro": "gerada aleatoriamente e negativa"
        },
        {
            "letra": "e)",
            "resposta": "S = [x \u2208 IR/ x = -17 ou x = -81]",
            "correta": "Nao",
            "tipoerro": "gerada aleatoriamente e positiva"
        }
    ],
    "atributosquestao": [
        {
            "enunciado": "Resolva a equa\u00e7\u00e3o:\nc) log<sub>12</sub>(104x\u00b2 + -7641x + 173452) = log<sub/>12</sub>(20x\u00b2 + 3x + 76)",
            "corretaspossiveis": "S = [x \u2208 IR/ x = 48 ou x = 43]",
            "corretas": 1,
            "aleatoriapositiva": 1,
            "aleatorianegativa": 3,
            "invertidapositiva": 0,
            "invertidanegativa": 0,
            "respostascorretas": "B"
        }
    ]
}