{
    "logaritmo": [
        {
            "a": 8,
            "b": 144,
            "c": 448,
            "x1": -4,
            "x2": -14,
            "resposta": "S = [x \u2208 IR/ x = -4 ou x = -14]"
        }
    ],
    "respostas": [
        {
            "letra": "a)",
            "resposta": "S = [x \u2208 IR/ x = 90 ou x = 65]",
            "correta": "Nao",
            "tipoerro": "gerada aleatoriamente e positiva"
        },
        {
            "letra": "b)",
            "resposta": "S = [x \u2208 IR/ x = 84 ou x = -28]",
            "correta": "Nao",
            "tipoerro": "gerada aleatoriamente e positiva"
        },
        {
            "letra": "c)",
            "resposta": "S = [x \u2208 IR/ x = -4 ou x = -14]",
            "correta": "Sim",
            "tipoerro": "nenhum"
        },
        {
            "letra": "d)",
            "resposta": "S = [x \u2208 IR/ x = -45 ou x = -30]",
            "correta": "Nao",
            "tipoerro": "gerada aleatoriamente e negativa"
        },
        {
            "letra": "e)",
            "resposta": "S = [x \u2208 IR/ x = -10 ou x = 0]",
            "correta": "Nao",
            "tipoerro": "invertida e negativa"
        }
    ],
    "atributosquestao": [
        {
            "enunciado": "Resolva a equa\u00e7\u00e3o:\nc) log<sub>183</sub>(48x\u00b2 + 209x + 525) = log<sub/>183</sub>(40x\u00b2 + 65x + 77)",
            "corretaspossiveis": "S = [x \u2208 IR/ x = -4 ou x = -14]",
            "corretas": 1,
            "aleatoriapositiva": 2,
            "aleatorianegativa": 1,
            "invertidapositiva": 0,
            "invertidanegativa": 1,
            "respostascorretas": "C"
        }
    ]
}