{
    "equacaoExponencial": [
        {
            "numFloatAleatorio01": 136.48,
            "numFloatAleatorio02": 89.47,
            "ordemDez01": 20,
            "ordemDez02": 21,
            "resposta": "M < N"
        }
    ],
    "respostas": [
        {
            "letra": "a)",
            "resposta": "M < N",
            "correta": "Sim",
            "tipoerro": "nenhum"
        },
        {
            "letra": "b)",
            "resposta": "M + N = 225,95 . 10<sup>41</sup>",
            "correta": "Nao",
            "tipoerro": "gerada aleatoriamente e positiva"
        },
        {
            "letra": "c)",
            "resposta": "M \u2265 N",
            "correta": "Nao",
            "tipoerro": "invertida e positiva"
        },
        {
            "letra": "d)",
            "resposta": "M . N = 12210,87 . 10<sup>41</sup>",
            "correta": "Nao",
            "tipoerro": "gerada aleatoriamente e positiva"
        },
        {
            "letra": "e)",
            "resposta": "M / N = 1,53 . 10<sup>-1</sup>",
            "correta": "Nao",
            "tipoerro": "gerada aleatoriamente e positiva"
        }
    ],
    "atributosquestao": [
        {
            "enunciado": "(UF-RN-modificada) Dados os n\u00fameros M = 136,48 . 10<sup>20</sup> e N = 89,47 . 10<sup>21</sup>. Pode-se afirmar que:",
            "corretaspossiveis": "M < N",
            "corretas": 1,
            "aleatoriapositiva": 3,
            "aleatorianegativa": 0,
            "invertidapositiva": 1,
            "invertidanegativa": 0,
            "respostascorretas": "A"
        }
    ]
}