{
    "equacaoExponencial": [
        {
            "numFloatAleatorio01": 481.83,
            "numFloatAleatorio02": 17.68,
            "ordemDez01": 88,
            "ordemDez02": 89,
            "resposta": "M \u2265 N"
        }
    ],
    "respostas": [
        {
            "letra": "a)",
            "resposta": "M + N = 499,51 \u00d7 10<sup>177</sup>",
            "correta": "Nao",
            "tipoerro": "gerada aleatoriamente e positiva"
        },
        {
            "letra": "b)",
            "resposta": "M < N",
            "correta": "Nao",
            "tipoerro": "invertida e positiva"
        },
        {
            "letra": "c)",
            "resposta": "M . N = 8518,75 \u00d7 10<sup>177</sup>",
            "correta": "Nao",
            "tipoerro": "gerada aleatoriamente e positiva"
        },
        {
            "letra": "d)",
            "resposta": "M / N = 27,25 \u00d7 10<sup>-1</sup>",
            "correta": "Nao",
            "tipoerro": "gerada aleatoriamente e positiva"
        },
        {
            "letra": "e)",
            "resposta": "M \u2265 N",
            "correta": "Sim",
            "tipoerro": "nenhum"
        }
    ],
    "atributosquestao": [
        {
            "enunciado": "(UF-RN-modificada) Dados os n\u00fameros M = 481,83 \u00d7 10<sup>88</sup> e N = 17,68 \u00d7 10<sup>89</sup>. Pode-se afirmar que:",
            "corretaspossiveis": "M \u2265 N",
            "corretas": 1,
            "aleatoriapositiva": 3,
            "aleatorianegativa": 0,
            "invertidapositiva": 1,
            "invertidanegativa": 0,
            "respostascorretas": "E"
        }
    ]
}