{
    "equacaoExponencial": [
        {
            "numFloatAleatorio01": 437.64,
            "numFloatAleatorio02": 88.37,
            "ordemDez01": 14,
            "ordemDez02": 15,
            "resposta": "M < N"
        }
    ],
    "respostas": [
        {
            "letra": "a)",
            "resposta": "M + N = 526,01 X 10^29",
            "correta": "Nao",
            "tipoerro": "gerada aleatoriamente e positiva"
        },
        {
            "letra": "b)",
            "resposta": "M < N",
            "correta": "Sim",
            "tipoerro": "nenhum"
        },
        {
            "letra": "c)",
            "resposta": "M . N = 38674,25 X 10^29",
            "correta": "Nao",
            "tipoerro": "gerada aleatoriamente e positiva"
        },
        {
            "letra": "d)",
            "resposta": "M \u2265 N",
            "correta": "Nao",
            "tipoerro": "invertida e positiva"
        },
        {
            "letra": "e)",
            "resposta": "M / N = 4,95 X 10^-1",
            "correta": "Nao",
            "tipoerro": "gerada aleatoriamente e positiva"
        }
    ],
    "atributosquestao": [
        {
            "enunciado": "(UF-RN-modificada) Dados os n\u00fameros M = 437,64 X 10^14 e N = 88,37 X 10^15. Pode-se afirmar que:",
            "corretaspossiveis": "M < N",
            "corretas": 1,
            "aleatoriapositiva": 3,
            "aleatorianegativa": 0,
            "invertidapositiva": 1,
            "invertidanegativa": 0,
            "respostascorretas": "B"
        }
    ]
}