{
    "equacaoExponencial": [
        {
            "numFloatAleatorio01": 535.46,
            "numFloatAleatorio02": 94.62,
            "ordemDez01": 90,
            "ordemDez02": 91,
            "resposta": "M < N"
        }
    ],
    "respostas": [
        {
            "letra": "a)",
            "resposta": "M + N = 630,08 \u00d7 10<sup>181</sup>",
            "correta": "Nao",
            "tipoerro": "gerada aleatoriamente e positiva"
        },
        {
            "letra": "b)",
            "resposta": "M < N",
            "correta": "Sim",
            "tipoerro": "nenhum"
        },
        {
            "letra": "c)",
            "resposta": "M \u2265 N",
            "correta": "Nao",
            "tipoerro": "invertida e positiva"
        },
        {
            "letra": "d)",
            "resposta": "M . N = 50665,23 \u00d7 10<sup>181</sup>",
            "correta": "Nao",
            "tipoerro": "gerada aleatoriamente e positiva"
        },
        {
            "letra": "e)",
            "resposta": "M / N = 5,66 \u00d7 10<sup>1</sup>",
            "correta": "Nao",
            "tipoerro": "gerada aleatoriamente e positiva"
        }
    ],
    "atributosquestao": [
        {
            "enunciado": "(UF-RN-modificada) Dados os n\u00fameros M = 535,46 \u00d7 10<sup>90</sup> e N = 94,62 \u00d7 10<sup>91</sup>. Pode-se afirmar que:",
            "corretaspossiveis": "M < N",
            "corretas": 1,
            "aleatoriapositiva": 3,
            "aleatorianegativa": 0,
            "invertidapositiva": 1,
            "invertidanegativa": 0,
            "respostascorretas": "B"
        }
    ]
}