{
    "equacaoExponencial": [
        {
            "base": 8300,
            "numMultiplicadorNumBase": 6,
            "expoente": 9700,
            "resposta": 0.000619
        }
    ],
    "respostas": [
        {
            "letra": "a)",
            "resposta": 0.000723,
            "correta": "Nao",
            "tipoerro": "invertida e positiva"
        },
        {
            "letra": "b)",
            "resposta": -0.000788,
            "correta": "Nao",
            "tipoerro": "gerada aleatoriamente e negativa"
        },
        {
            "letra": "c)",
            "resposta": 0.000619,
            "correta": "Sim",
            "tipoerro": "nenhum"
        },
        {
            "letra": "d)",
            "resposta": -0.00885,
            "correta": "Nao",
            "tipoerro": "gerada aleatoriamente e negativa"
        },
        {
            "letra": "e)",
            "resposta": -0.001147,
            "correta": "Nao",
            "tipoerro": "gerada aleatoriamente e negativa"
        }
    ],
    "atributosquestao": [
        {
            "enunciado": "Uma subst\u00e2ncia radioativa est\u00e1 em processo de desintegra\u00e7\u00e3o, de modo que no instante t a quantidade n\u00e3o desintegrada \u00e9 A(t) = A(0).e^(-9700.t), em que A(0) indica a quantidade de subst\u00e2ncia no instante t = 0. Calcule o tempo necess\u00e1rio para que a quantidade inicial dividida por 49800 se desintegre.",
            "corretaspossiveis": 0.000619,
            "corretas": 1,
            "aleatoriapositiva": 0,
            "aleatorianegativa": 3,
            "invertidapositiva": 1,
            "invertidanegativa": 0,
            "respostascorretas": "C"
        }
    ]
}